LICENSE
MANIFEST.in
README.org
README.rst
aiotkinter.py
setup.py
aiotkinter.egg-info/PKG-INFO
aiotkinter.egg-info/SOURCES.txt
aiotkinter.egg-info/dependency_links.txt
aiotkinter.egg-info/top_level.txt