Metadata-Version: 1.1
Name: aiotkinter
Version: 0.2
Summary: An asyncio API for the Tkinter event loop
Home-page: https://github.com/montag451/aiotkinter
Author: montag451
Author-email: montag451 at laposte.net
License: UNKNOWN
Platform: UNKNOWN
Classifier: Development Status :: 3 - Alpha
Classifier: Intended Audience :: Developers
Classifier: License :: OSI Approved :: MIT License
Classifier: Operating System :: Unix
Classifier: Programming Language :: Python
Classifier: Programming Language :: Python :: 3
Classifier: Programming Language :: Python :: 3.3
